sortasaurus_rex/__init__.py
sortasaurus_rex/srex.py
sortasaurus_rex/utilities/__init__.py
sortasaurus_rex/utilities/classifier.py
sortasaurus_rex/utilities/custom_exceptions.py
sortasaurus_rex/utilities/directories_handler.py
test/__init__.py
test/test_srex.py
sortasaurus_rex-0.4.0.dist-info/LICENSE
sortasaurus_rex-0.4.0.dist-info/METADATA
sortasaurus_rex-0.4.0.dist-info/WHEEL
sortasaurus_rex-0.4.0.dist-info/entry_points.txt
sortasaurus_rex-0.4.0.dist-info/top_level.txt
sortasaurus_rex-0.4.0.dist-info/RECORD
