Metadata-Version: 2.1
Name: sortasaurus_rex
Version: 0.4.0
License-File: LICENSE
Requires-Dist: tqdm ~=4.66.4
Requires-Dist: python-dotenv
Requires-Dist: setuptools
Requires-Dist: wheel
Requires-Dist: twine
Requires-Dist: build
